funlab/core/__init__.py
funlab/core/appbase.py
funlab/core/auth.py
funlab/core/config.py
funlab/core/dbmgr.py
funlab/core/jinja_filters.py
funlab/core/menu.py
funlab/core/plugin.py
funlab/utils/__init__.py
funlab/utils/dtts.py
funlab/utils/lang.py
funlab/utils/log.py
funlab/utils/url.py
funlab/utils/vars2env.py
funlab_libs-0.3.8.dist-info/LICENSE
funlab_libs-0.3.8.dist-info/METADATA
funlab_libs-0.3.8.dist-info/WHEEL
funlab_libs-0.3.8.dist-info/RECORD
