Metadata-Version: 2.1
Name: funlab-libs
Version: 0.3.8
Summary: Some core libraries for funlab-flaskr.
Home-page: https://github.com/sunnylin13/funlab-libs
License: MIT
Author: SunnyLin
Author-email: 013.lin@gmail.com
Requires-Python: >=3.11,<4.0
Classifier: License :: OSI Approved :: MIT License
Classifier: Programming Language :: Python :: 3
Classifier: Programming Language :: Python :: 3.11
Classifier: Programming Language :: Python :: 3.12
Requires-Dist: colorama (>=0.4.6,<0.5.0)
Requires-Dist: cryptography (>=42.0.7,<43.0.0)
Requires-Dist: flask-caching (>=2.3.0,<3.0.0)
Requires-Dist: pandas (>=2.2.2,<3.0.0)
Requires-Dist: sqlalchemy (>=2.0.30,<3.0.0)
Project-URL: Repository, https://github.com/sunnylin13/funlab-libs
